energy_vad/__init__.py
energy_vad-1.0.0.dist-info/LICENSE.md
energy_vad-1.0.0.dist-info/METADATA
energy_vad-1.0.0.dist-info/WHEEL
energy_vad-1.0.0.dist-info/top_level.txt
energy_vad-1.0.0.dist-info/zip-safe
energy_vad-1.0.0.dist-info/RECORD
