Metadata-Version: 2.1
Name: energy-vad
Version: 1.0.0
Summary: Intents for Home Assistant
Author-email: The Home Assistant Authors <hello@home-assistant.io>
License: MIT
Project-URL: Source Code, https://github.com/rhasspy/energy-vad
Keywords: home,assistant,intent,recognition
Platform: any
Classifier: Development Status :: 3 - Alpha
Classifier: Intended Audience :: Developers
Classifier: Topic :: Text Processing :: Linguistic
Classifier: License :: OSI Approved :: MIT License
Classifier: Programming Language :: Python :: 3.7
Classifier: Programming Language :: Python :: 3.8
Classifier: Programming Language :: Python :: 3.9
Classifier: Programming Language :: Python :: 3.10
Classifier: Programming Language :: Python :: 3.11
Classifier: Programming Language :: Python :: 3.12
Requires-Python: >=3.7.0
License-File: LICENSE.md
